picows/__init__.py
picows/picows.cpython-312-x86_64-linux-gnu.so
picows/picows.pxd
picows/picows.pyi
picows/picows.pyx
picows/picows_compat.h
picows/py.typed
picows-1.10.2.dist-info/METADATA
picows-1.10.2.dist-info/WHEEL
picows-1.10.2.dist-info/top_level.txt
picows-1.10.2.dist-info/RECORD
picows-1.10.2.dist-info/licenses/LICENSE
