Metadata-Version: 2.4
Name: picows
Version: 1.10.2
Summary: Ultra-fast websocket client and server for asyncio
Author-email: Taras Kozlov <tarasko.projects@gmail.com>
Project-URL: Homepage, https://github.com/tarasko/picows
Project-URL: Repository, https://github.com/tarasko/picows
Project-URL: Issues, https://github.com/tarasko/picows/issues
Project-URL: Documentation, https://picows.readthedocs.io/en/latest
Keywords: websocket,networking
Classifier: Development Status :: 5 - Production/Stable
Classifier: Framework :: AsyncIO
Classifier: Intended Audience :: Developers
Classifier: Operating System :: POSIX
Classifier: Operating System :: MacOS :: MacOS X
Classifier: Operating System :: Microsoft :: Windows
Classifier: Programming Language :: Python :: 3 :: Only
Classifier: Programming Language :: Python :: 3.9
Classifier: Programming Language :: Python :: 3.10
Classifier: Programming Language :: Python :: 3.11
Classifier: Programming Language :: Python :: 3.12
Classifier: Programming Language :: Python :: 3.13
Classifier: Programming Language :: Cython
Classifier: Programming Language :: Python :: Implementation :: CPython
Classifier: Topic :: System :: Networking
Requires-Python: >=3.9
License-File: LICENSE
Requires-Dist: multidict
Dynamic: license-file
